archivey/__init__.py
archivey/__main__.py
archivey/archive_reader.py
archivey/config.py
archivey/core.py
archivey/exceptions.py
archivey/filters.py
archivey/types.py
archivey/formats/__init__.py
archivey/formats/compressed_streams.py
archivey/formats/folder_reader.py
archivey/formats/format_detection.py
archivey/formats/rar_reader.py
archivey/formats/sevenzip_reader.py
archivey/formats/single_file_reader.py
archivey/formats/tar_reader.py
archivey/formats/zip_reader.py
archivey/internal/__init__.py
archivey/internal/archive_stream.py
archivey/internal/base_reader.py
archivey/internal/cli.py
archivey/internal/dependency_checker.py
archivey/internal/extraction_helper.py
archivey/internal/io_helpers.py
archivey/internal/utils.py
archivey-0.1.0a4.dist-info/METADATA
archivey-0.1.0a4.dist-info/WHEEL
archivey-0.1.0a4.dist-info/entry_points.txt
archivey-0.1.0a4.dist-info/licenses/LICENSE
archivey-0.1.0a4.dist-info/RECORD
